pydantic_extensions/__init__.py
pydantic_extensions-0.1.0.dist-info/licenses/LICENSE
pydantic_extensions-0.1.0.dist-info/METADATA
pydantic_extensions-0.1.0.dist-info/WHEEL
pydantic_extensions-0.1.0.dist-info/top_level.txt
pydantic_extensions-0.1.0.dist-info/RECORD
