Metadata-Version: 2.4
Name: pydantic-extensions
Version: 0.1.0
Summary: Toolkit for pydantic(dynamic fields + pagination + variable fields list) 
License: MIT License
Requires-Python: >=3.12
License-File: LICENSE
Dynamic: license-file
